pylfg/BUILD
pylfg/TUI/BUILD
pylfg/TUI/TUI.py
pylfg/TUI/TUI2.py
pylfg/TUI/TUI5.py
pylfg/TUI/TUI6.py
pylfg/TUI/TUI7.py
pylfg/TUI/TUI8.py
pylfg/TUI/TUI9.py
pylfg/TUI/Tui3.py
pylfg/TUI/Tui4.py
pylfg/TUI/command.py
pylfg/WebUI/BUILD
pylfg/WebUI/main.py
pylfg/WebUI/templates/Index2.html
pylfg/WebUI/templates/grammar_view.html
pylfg/WebUI/templates/grammar_writing.html
pylfg/WebUI/templates/help.html
pylfg/WebUI/templates/index.html
pylfg/WebUI/templates/index3.html
pylfg/WebUI/templates/input_view.html
pylfg/WebUI/templates/input_view2.html
pylfg/WebUI/templates/results_view.html
pylfg/WebUI/templates/results_view2.html
pylfg/WebUI/templates/script.js
pylfg/WebUI/templates/scripts.js
pylfg/WebUI/templates/styles.css
pylfg/WebUI/templates/upload_success.html
pylfg/WebUI/views/BUILD
pylfg/WebUI/views/grammar.py
pylfg/WebUI/views/help.py
pylfg/WebUI/views/history.py
pylfg/__init__.py
pylfg/fst.py
pylfg/parse_tree.py
pylfg/parser.py
pylfg/parser_gen.py
pylfg/transfer/__init__.py
pylfg/transfer/transfer_rules/EN_FR_sample.lfg
pylfg/transfer/translator.py
pylfg/xle.py
pylfg/xlfg.py
pylfg-0.1.1a0.dist-info/LICENSE
pylfg-0.1.1a0.dist-info/WHEEL
pylfg-0.1.1a0.dist-info/METADATA
pylfg-0.1.1a0.dist-info/RECORD
