Metadata-Version: 2.1
Name: pylfg
Version: 0.1.1a0
Summary: PyLFG is a Python library for working within the Lexical Functional Grammar (LFG) formalism. It provides a set of classes and methods for representing and manipulating LFG structures, including lexical functional structures (f-structures) and c-structures.
License: MIT
Author: SekouDiaoNlp
Author-email: diao.sekou.nlp@gmail.com
Requires-Python: >=3.11,<4.0
Classifier: License :: OSI Approved :: MIT License
Classifier: Programming Language :: Python :: 3
Classifier: Programming Language :: Python :: 3.11
Requires-Dist: PlyPlus (>=0.7.5,<0.8.0)
Requires-Dist: click (>=8.1.3,<9.0.0)
Requires-Dist: fastapi (>=0.89.1,<0.90.0)
Requires-Dist: matplotlib (>=3.6.3,<4.0.0)
Requires-Dist: networkx (>=3.0,<4.0)
Requires-Dist: rich (>=13.3.1,<14.0.0)
Requires-Dist: textual (>=0.10.1,<0.11.0)
Requires-Dist: textual-imageview (>=0.1.1,<0.2.0)
